[
  {
    "id": "2",
    "name": "何の成果も、得られませんでした！",
    "audioResourcePath": "/audio/nannnoseikamo.mp3",
    "youTubeVideoUrl": "https://youtu.be/doUMy8NYw-Q?si=bL1RX14lc-rIpkJG&t=596"
  },
  {
    "id": "2",
    "name": "嵌められた~~!!!",
    "audioResourcePath": "/audio/hamerareta.mp3",
    "youTubeVideoUrl": "https://youtu.be/doUMy8NYw-Q?si=bL1RX14lc-rIpkJG&t=596"
  },
  {
    "id": "2",
    "name": "ｳﾜ-!!!なんか追いかけてくる！",
    "audioResourcePath": "/audio/nannkaoikaketekuru.mp3",
    "youTubeVideoUrl": "https://youtu.be/doUMy8NYw-Q?si=bL1RX14lc-rIpkJG&t=596"
  },
  {
    "id": "2",
    "name": "ふぅ......",
    "audioResourcePath": "/audio/huu.mp3",
    "youTubeVideoUrl": "https://youtu.be/doUMy8NYw-Q?si=bL1RX14lc-rIpkJG&t=596"
  },
  {
    "id": "2",
    "name": "きよまろの仇じゃ--!!!",
    "audioResourcePath": "/audio/kiyomarono.mp3",
    "youTubeVideoUrl": "https://youtu.be/doUMy8NYw-Q?si=bL1RX14lc-rIpkJG&t=596"
  },
  {
    "id": "2",
    "name": "力が欲しいんだよ我輩もさ",
    "audioResourcePath": "/audio/tikaraga.mp3",
    "youTubeVideoUrl": "https://youtu.be/doUMy8NYw-Q?si=bL1RX14lc-rIpkJG&t=596"
  },
  {
    "id": "2",
    "name": "面白ければ、それでヨシ！",
    "audioResourcePath": "/audio/omoshirokereba.mp3",
    "youTubeVideoUrl": "https://youtu.be/doUMy8NYw-Q?si=bL1RX14lc-rIpkJG&t=596"
  },
  {
    "id": "2",
    "name": "力を手にしたいな",
    "audioResourcePath": "/audio/tikarawotenisitai.mp3",
    "youTubeVideoUrl": "https://youtu.be/doUMy8NYw-Q?si=bL1RX14lc-rIpkJG&t=596"
  },
  {
    "id": "2",
    "name": "Re:ゼロから始めるARKヒモ生活",
    "audioResourcePath": "/audio/zerokarahazimeru.mp3",
    "youTubeVideoUrl": "https://youtu.be/doUMy8NYw-Q?si=bL1RX14lc-rIpkJG&t=596"
  },
  {
    "id": "2",
    "name": "しつれいしつれ〜い",
    "audioResourcePath": "/audio/situreisiturei.mp3",
    "youTubeVideoUrl": "https://youtu.be/doUMy8NYw-Q?si=bL1RX14lc-rIpkJG&t=596"
  },
  {
    "id": "2",
    "name": "シェイクシェイクブギーな胸騒ぎ♪(略)",
    "audioResourcePath": "/audio/shakeshake.mp3",
    "youTubeVideoUrl": "https://youtu.be/doUMy8NYw-Q?si=bL1RX14lc-rIpkJG&t=596"
  },
  {
    "id": "2",
    "name": "ありがとねありがとね〜",
    "audioResourcePath": "/audio/arigatonearigatone.mp3",
    "youTubeVideoUrl": "https://youtu.be/doUMy8NYw-Q?si=bL1RX14lc-rIpkJG&t=596"
  },
  {
    "id": "2",
    "name": "めでたい！めでたすぎるちょっと",
    "audioResourcePath": "/audio/medetai.mp3",
    "youTubeVideoUrl": "https://youtu.be/doUMy8NYw-Q?si=bL1RX14lc-rIpkJG&t=596"
  },
  {
    "id": "2",
    "name": "あぶねーあぶねー",
    "audioResourcePath": "/audio/abuneabune.mp3",
    "youTubeVideoUrl": "https://youtu.be/doUMy8NYw-Q?si=bL1RX14lc-rIpkJG&t=596"
  },
  {
    "id": "2",
    "name": "お姉ちゃん!?",
    "audioResourcePath": "/audio/oneetyan1.mp3",
    "youTubeVideoUrl": "https://youtu.be/doUMy8NYw-Q?si=bL1RX14lc-rIpkJG&t=596"
  },
  {
    "id": "2",
    "name": "ﾌｴｯ!?へっ？",
    "audioResourcePath": "/audio/huehe.mp3",
    "youTubeVideoUrl": "https://youtu.be/doUMy8NYw-Q?si=bL1RX14lc-rIpkJG&t=596"
  },
  {
    "id": "2",
    "name": "お姉ちゃん??",
    "audioResourcePath": "/audio/onetyan2.mp3",
    "youTubeVideoUrl": "https://youtu.be/doUMy8NYw-Q?si=bL1RX14lc-rIpkJG&t=596"
  },
  {
    "id": "2",
    "name": "お姉ちゃんだ(確信)",
    "audioResourcePath": "/audio/onetyan3.mp3",
    "youTubeVideoUrl": "https://youtu.be/doUMy8NYw-Q?si=bL1RX14lc-rIpkJG&t=596"
  },
  {
    "id": "2",
    "name": "やばばばば(略)",
    "audioResourcePath": "/audio/yababa.mp3",
    "youTubeVideoUrl": "https://youtu.be/doUMy8NYw-Q?si=bL1RX14lc-rIpkJG&t=596"
  },
  {
    "id": "2",
    "name": "へっ、お姉ちゃん!?",
    "audioResourcePath": "/audio/onetyan4.mp3",
    "youTubeVideoUrl": "https://youtu.be/doUMy8NYw-Q?si=bL1RX14lc-rIpkJG&t=596"
  },
  {
    "id": "2",
    "name": "ﾊｱﾀﾞｱﾀﾞ",
    "audioResourcePath": "/audio/haadaa.mp3",
    "youTubeVideoUrl": "https://youtu.be/doUMy8NYw-Q?si=bL1RX14lc-rIpkJG&t=596"
  },
  {
    "id": "2",
    "name": "たーすけて",
    "audioResourcePath": "/audio/dasukete.mp3",
    "youTubeVideoUrl": "https://youtu.be/doUMy8NYw-Q?si=bL1RX14lc-rIpkJG&t=596"
  },
  {
    "id": "2",
    "name": "やはりそうなるのかァ↑",
    "audioResourcePath": "/audio/yaharisounarunoka.mp3",
    "youTubeVideoUrl": "https://youtu.be/doUMy8NYw-Q?si=bL1RX14lc-rIpkJG&t=596"
  },
  {
    "id": "2",
    "name": "ﾅﾅﾅﾅﾅﾅﾅ",
    "audioResourcePath": "/audio/nananananana.mp3",
    "youTubeVideoUrl": "https://youtu.be/doUMy8NYw-Q?si=bL1RX14lc-rIpkJG&t=596"
  },
  {
    "id": "2",
    "name": "意地悪だ、意地悪だ",
    "audioResourcePath": "/audio/iziwaruda.mp3",
    "youTubeVideoUrl": "https://youtu.be/doUMy8NYw-Q?si=bL1RX14lc-rIpkJG&t=596"
  },
  {
    "id": "2",
    "name": "いーやーいーや、いやよいやよ",
    "audioResourcePath": "/audio/i-yai-ya.mp3",
    "youTubeVideoUrl": "https://youtu.be/doUMy8NYw-Q?si=bL1RX14lc-rIpkJG&t=596"
  },
  {
    "id": "2",
    "name": "いぃえ",
    "audioResourcePath": "/audio/iie.mp3",
    "youTubeVideoUrl": "https://youtu.be/doUMy8NYw-Q?si=bL1RX14lc-rIpkJG&t=596"
  },
  {
    "id": "2",
    "name": "お主も我輩なのか!?",
    "audioResourcePath": "/audio/onushimo.mp3",
    "youTubeVideoUrl": "https://youtu.be/doUMy8NYw-Q?si=bL1RX14lc-rIpkJG&t=596"
  },
  {
    "id": "2",
    "name": "んなぁ",
    "audioResourcePath": "/audio/nnaa.mp3",
    "youTubeVideoUrl": "https://youtu.be/doUMy8NYw-Q?si=bL1RX14lc-rIpkJG&t=596"
  },
  {
    "id": "2",
    "name": "ﾅﾊ、そんなあ",
    "audioResourcePath": "/audio/nasonnna.mp3",
    "youTubeVideoUrl": "https://youtu.be/doUMy8NYw-Q?si=bL1RX14lc-rIpkJG&t=596"
  },
  {
    "id": "2",
    "name": "ｷﾞｬｱー嘘！",
    "audioResourcePath": "/audio/gyauso.mp3",
    "youTubeVideoUrl": "https://youtu.be/doUMy8NYw-Q?si=bL1RX14lc-rIpkJG&t=596"
  },
  {
    "id": "2",
    "name": "頼む、間に合ってくれ、我輩の肉球!",
    "audioResourcePath": "/audio/tanomumaniattekure.mp3",
    "youTubeVideoUrl": "https://youtu.be/doUMy8NYw-Q?si=bL1RX14lc-rIpkJG&t=596"
  },
  {
    "id": "2",
    "name": "パトランプ本体の説3",
    "audioResourcePath": "/audio/setu3.mp3",
    "youTubeVideoUrl": "https://youtu.be/doUMy8NYw-Q?si=bL1RX14lc-rIpkJG&t=596"
  },
  {
    "id": "2",
    "name": "大変だぁよねぇそうだよねぇ",
    "audioResourcePath": "/audio/taihenndayone.mp3",
    "youTubeVideoUrl": "https://youtu.be/doUMy8NYw-Q?si=bL1RX14lc-rIpkJG&t=596"
  },
  {
    "id": "2",
    "name": "ちょっとぉ",
    "audioResourcePath": "/audio/tyotto.mp3",
    "youTubeVideoUrl": "https://youtu.be/doUMy8NYw-Q?si=bL1RX14lc-rIpkJG&t=596"
  },
  {
    "id": "2",
    "name": "なむ!?なむなむなむ",
    "audioResourcePath": "/audio/namunamu.mp3",
    "youTubeVideoUrl": "https://youtu.be/doUMy8NYw-Q?si=bL1RX14lc-rIpkJG&t=596"
  },
  {
    "id": "2",
    "name": "ナイスやね!",
    "audioResourcePath": "/audio/naisuyane.mp3",
    "youTubeVideoUrl": "https://youtu.be/doUMy8NYw-Q?si=bL1RX14lc-rIpkJG&t=596"
  },
  {
    "id": "2",
    "name": "まあね正直、我輩ね",
    "audioResourcePath": "/audio/maanesyouzikiwagahaine.mp3",
    "youTubeVideoUrl": "https://youtu.be/doUMy8NYw-Q?si=bL1RX14lc-rIpkJG&t=596"
  },
  {
    "id": "2",
    "name": "何の話かい？(すっとぼけ)",
    "audioResourcePath": "/audio/nannnohanasikai.mp3",
    "youTubeVideoUrl": "https://youtu.be/doUMy8NYw-Q?si=bL1RX14lc-rIpkJG&t=596"
  },
  {
    "id": "2",
    "name": "やばばば危ないよ~(危ないよ~)",
    "audioResourcePath": "/audio/yabababaabunaiyo.mp3",
    "youTubeVideoUrl": "https://youtu.be/doUMy8NYw-Q?si=bL1RX14lc-rIpkJG&t=596"
  },
  {
    "id": "2",
    "name": "心がふたつある~~!",
    "audioResourcePath": "/audio/kokoroga.mp3",
    "youTubeVideoUrl": "https://youtu.be/doUMy8NYw-Q?si=bL1RX14lc-rIpkJG&t=596"
  },
  {
    "id": "2",
    "name": "さあ~ではではでは~",
    "audioResourcePath": "/audio/sadewadewadewa.mp3",
    "youTubeVideoUrl": "https://youtu.be/doUMy8NYw-Q?si=bL1RX14lc-rIpkJG&t=596"
  },
  {
    "id": "2",
    "name": "お願いだあ",
    "audioResourcePath": "/audio/onegaida.mp3",
    "youTubeVideoUrl": "https://youtu.be/doUMy8NYw-Q?si=bL1RX14lc-rIpkJG&t=596"
  },
  {
    "id": "2",
    "name": "鳴き声+頼むよ×2",
    "audioResourcePath": "/audio/natanomuyo.mp3",
    "youTubeVideoUrl": "https://youtu.be/doUMy8NYw-Q?si=bL1RX14lc-rIpkJG&t=596"
  },
  {
    "id": "2",
    "name": "つれえよなあ、まじか!",
    "audioResourcePath": "/audio/tureyona-majika.mp3",
    "youTubeVideoUrl": "https://youtu.be/doUMy8NYw-Q?si=bL1RX14lc-rIpkJG&t=596"
  },
  {
    "id": "2",
    "name": "つれえよなあ(普段)",
    "audioResourcePath": "/audio/tureyona4.mp3",
    "youTubeVideoUrl": "https://youtu.be/doUMy8NYw-Q?si=bL1RX14lc-rIpkJG&t=596"
  },
  {
    "id": "2",
    "name": "つれえよなあ(明るめ)",
    "audioResourcePath": "/audio/tureyona3.mp3",
    "youTubeVideoUrl": "https://youtu.be/doUMy8NYw-Q?si=bL1RX14lc-rIpkJG&t=596"
  },
  {
    "id": "2",
    "name": "つれえよなあ(動画用)",
    "audioResourcePath": "/audio/tureyona2.mp3",
    "youTubeVideoUrl": "https://youtu.be/doUMy8NYw-Q?si=bL1RX14lc-rIpkJG&t=596"
  },
  {
    "id": "2",
    "name": "(初期猫)我輩とっても嬉しいぞ",
    "audioResourcePath": "/audio/wagahaitottemo.mp3",
    "youTubeVideoUrl": "https://youtu.be/doUMy8NYw-Q?si=bL1RX14lc-rIpkJG&t=596"
  },
  {
    "id": "2",
    "name": "(初期猫)やったぞ〜〜！",
    "audioResourcePath": "/audio/yattazo-.mp3",
    "youTubeVideoUrl": "https://youtu.be/doUMy8NYw-Q?si=bL1RX14lc-rIpkJG&t=596"
  },
  {
    "id": "2",
    "name": "(初期猫)どうなることかと思ったゾ",
    "audioResourcePath": "/audio/dounarukotokato.mp3",
    "youTubeVideoUrl": "https://youtu.be/doUMy8NYw-Q?si=bL1RX14lc-rIpkJG&t=596"
  },
  {
    "id": "2",
    "name": "(初期猫)それすごいわかるゾ",
    "audioResourcePath": "/audio/soresugoiwakaruzo.mp3",
    "youTubeVideoUrl": "https://youtu.be/doUMy8NYw-Q?si=bL1RX14lc-rIpkJG&t=596"
  },
  {
    "id": "2",
    "name": "(初期猫)嬉しい",
    "audioResourcePath": "/audio/uresii.mp3",
    "youTubeVideoUrl": "https://youtu.be/doUMy8NYw-Q?si=bL1RX14lc-rIpkJG&t=596"
  },
  {
    "id": "2",
    "name": "(初期猫)ありガントありガント",
    "audioResourcePath": "/audio/arigannto*2.mp3",
    "youTubeVideoUrl": "https://youtu.be/doUMy8NYw-Q?si=bL1RX14lc-rIpkJG&t=596"
  },
  {
    "id": "2",
    "name": "(初期猫)頑張るゾ",
    "audioResourcePath": "/audio/ganbaruzo.mp3",
    "youTubeVideoUrl": "https://youtu.be/doUMy8NYw-Q?si=bL1RX14lc-rIpkJG&t=596"
  },
  {
    "id": "2",
    "name": "(初期猫)きたー！",
    "audioResourcePath": "/audio/kita-.mp3",
    "youTubeVideoUrl": "https://youtu.be/doUMy8NYw-Q?si=bL1RX14lc-rIpkJG&t=596"
  },
  {
    "id": "2",
    "name": "(初期猫)我輩ってフェニックスだからサ~",
    "audioResourcePath": "/audio/fenikkusu.mp3",
    "youTubeVideoUrl": "https://youtu.be/doUMy8NYw-Q?si=bL1RX14lc-rIpkJG&t=596"
  },
  {
    "id": "2",
    "name": "(初期猫)ごめんなさい",
    "audioResourcePath": "/audio/gomennasai.mp3",
    "youTubeVideoUrl": "https://youtu.be/doUMy8NYw-Q?si=bL1RX14lc-rIpkJG&t=596"
  },
  {
    "id": "2",
    "name": "チョットマチーナ!チョットマチーナ!",
    "audioResourcePath": "/audio/thotto.mp3",
    "youTubeVideoUrl": "https://youtu.be/doUMy8NYw-Q?si=bL1RX14lc-rIpkJG&t=596"
  },
  {
    "id": "2",
    "name": "ﾊﾞﾘﾊﾞﾘﾊﾞﾘﾊﾞﾘﾊﾞﾘﾊﾞﾘ",
    "audioResourcePath": "/audio/baribari.mp3",
    "youTubeVideoUrl": "https://youtu.be/doUMy8NYw-Q?si=bL1RX14lc-rIpkJG&t=596"
  },
  {
    "id": "2",
    "name": "筍のこのこ虎視眈々",
    "audioResourcePath": "/audio/takenokonokonoko.mp3",
    "youTubeVideoUrl": "https://youtu.be/doUMy8NYw-Q?si=bL1RX14lc-rIpkJG&t=596"
  },
  {
    "id": "2",
    "name": "がにさす",
    "audioResourcePath": "/audio/ganisasu.mp3",
    "youTubeVideoUrl": "https://youtu.be/doUMy8NYw-Q?si=bL1RX14lc-rIpkJG&t=596"
  },
  {
    "id": "2",
    "name": "ﾅﾝﾃｺﾄ!?ﾅﾝﾃｺﾄ",
    "audioResourcePath": "/audio/nanntekoto*2.mp3",
    "youTubeVideoUrl": "https://youtu.be/doUMy8NYw-Q?si=bL1RX14lc-rIpkJG&t=596"
  },
  {
    "id": "2",
    "name": "(音量注意)はあ--!!!やった---!",
    "audioResourcePath": "/audio/ha-yatta-.mp3",
    "youTubeVideoUrl": "https://youtu.be/doUMy8NYw-Q?si=bL1RX14lc-rIpkJG&t=596"
  },
  {
    "id": "2",
    "name": "てんてんてーんてててててててーん",
    "audioResourcePath": "/audio/tentente-nn.mp3",
    "youTubeVideoUrl": "https://youtu.be/doUMy8NYw-Q?si=bL1RX14lc-rIpkJG&t=596"
  },
  {
    "id": "2",
    "name": "しょんぼりぼりぼりぼり太郎",
    "audioResourcePath": "/audio/shonbori.mp3",
    "youTubeVideoUrl": "https://youtu.be/doUMy8NYw-Q?si=bL1RX14lc-rIpkJG&t=596"
  },
  {
    "id": "2",
    "name": "ありガント",
    "audioResourcePath": "/audio/58E70DD1-F5B8-4090-962F-3D361050C0D3.mp3",
    "youTubeVideoUrl": "https://youtu.be/doUMy8NYw-Q?si=bL1RX14lc-rIpkJG&t=596"
  },
  {
    "id": "3",
    "name": "げげげげ~~(強)",
    "audioResourcePath": "/audio/げげげげ(強).mp3",
    "youTubeVideoUrl": "https://www.youtube.com/live/Qt9zb0nIhdg?si=Lii4WFeFoAfyDewL&t=11399"
  },
  {
    "id": "4",
    "name": "ブライト艦長",
    "audioResourcePath": "/audio/ブライト.mp3",
    "youTubeVideoUrl": "https://www.youtube.com/live/Qt9zb0nIhdg?si=5rMj10M8XrzUBH7M&t=11397"
  },
  {
    "id": "5",
    "name": "嫌だ嫌だ",
    "audioResourcePath": "/audio/iyada.mp3",
    "youTubeVideoUrl": "https://www.youtube.com/shorts/VFROAk8WS4g?t=10"
  },
  {
    "id": "6",
    "name": "なァアアア!!(歓喜)",
    "audioResourcePath": "/audio/naaa.mp3",
    "youTubeVideoUrl": "https://www.youtube.com/shorts/VFROAk8WS4g?t=10"
  },
  {
    "id": "7",
    "name": "やぁったぁ!アハー!",
    "audioResourcePath": "/audio/yatta.mp3",
    "youTubeVideoUrl": "https://www.youtube.com/shorts/VFROAk8WS4g?t=10"
  },
  {
    "id": "8",
    "name": "あはーはー(悲しみ)",
    "audioResourcePath": "/audio/naha.mp3",
    "youTubeVideoUrl": "https://www.youtube.com/shorts/VFROAk8WS4g?t=10"
  },
  {
    "id": "9",
    "name": "あの、大丈夫です",
    "audioResourcePath": "/audio/daizyoubudesu.mp3",
    "youTubeVideoUrl": "https://www.youtube.com/shorts/VFROAk8WS4g?t=10"
  },
  {
    "id": "10",
    "name": "バズ・ライトイヤーかな",
    "audioResourcePath": "/audio/bazuraitoiya-kana.mp3",
    "youTubeVideoUrl": "https://www.youtube.com/shorts/VFROAk8WS4g?t=10"
  },
  {
    "id": "11",
    "name": "まことに、まことに?",
    "audioResourcePath": "/audio/makotoni.mp3",
    "youTubeVideoUrl": "https://www.youtube.com/shorts/VFROAk8WS4g?t=10"
  },
  {
    "id": "12",
    "name": "アハハ",
    "audioResourcePath": "/audio/warai.mp3",
    "youTubeVideoUrl": "https://www.youtube.com/shorts/VFROAk8WS4g?t=10"
  },
  {
    "id": "13",
    "name": "ﾊｯ",
    "audioResourcePath": "/audio/ha.mp3",
    "youTubeVideoUrl": "https://www.youtube.com/shorts/VFROAk8WS4g?t=10"
  },
  {
    "id": "14",
    "name": "あらららららら",
    "audioResourcePath": "/audio/ararara.mp3",
    "youTubeVideoUrl": "https://www.youtube.com/shorts/VFROAk8WS4g?t=10"
  },
  {
    "id": "15",
    "name": "嬉しいね",
    "audioResourcePath": "/audio/ureshine.mp3",
    "youTubeVideoUrl": "https://www.youtube.com/shorts/VFROAk8WS4g?t=10"
  },
  {
    "id": "16",
    "name": "イヤァ!",
    "audioResourcePath": "/audio/iya.mp3",
    "youTubeVideoUrl": "https://www.youtube.com/shorts/VFROAk8WS4g?t=10"
  },
  {
    "id": "17",
    "name": "パトランプ本体の説",
    "audioResourcePath": "/audio/patoranpu.mp3",
    "youTubeVideoUrl": "https://www.youtube.com/shorts/VFROAk8WS4g?t=10"
  },
  {
    "id": "18",
    "name": "おいしょ、とととと",
    "audioResourcePath": "/audio/unsho.mp3",
    "youTubeVideoUrl": "https://youtu.be/doUMy8NYw-Q?si=bL1RX14lc-rIpkJG&t=596"
  },
  {
    "id": "19",
    "name": "アハハハハ",
    "audioResourcePath": "/audio/ahaha2.mp3",
    "youTubeVideoUrl": "https://www.youtube.com/live/Qt9zb0nIhdg?si=Lii4WFeFoAfyDewL&t=11399"
  },
  {
    "id": "20",
    "name": "行けた行けた行けた",
    "audioResourcePath": "/audio/iketaiketa.mp3",
    "youTubeVideoUrl": "https://www.youtube.com/live/Qt9zb0nIhdg?si=5rMj10M8XrzUBH7M&t=11397"
  },
  {
    "id": "21",
    "name": "キタキタキタキタキタ",
    "audioResourcePath": "/audio/kitakitakita.mp3",
    "youTubeVideoUrl": "https://www.youtube.com/shorts/VFROAk8WS4g?t=10"
  },
  {
    "id": "22",
    "name": "ナハハ",
    "audioResourcePath": "/audio/nahaha.mp3",
    "youTubeVideoUrl": "https://www.youtube.com/shorts/VFROAk8WS4g?t=10"
  },
  {
    "id": "23",
    "name": "やばいやばい",
    "audioResourcePath": "/audio/yabai.mp3",
    "youTubeVideoUrl": "https://www.youtube.com/shorts/VFROAk8WS4g?t=10"
  },
  {
    "id": "24",
    "name": "パトランプ本体の説2",
    "audioResourcePath": "/audio/patoranpu2.mp3",
    "youTubeVideoUrl": "https://www.youtube.com/shorts/VFROAk8WS4g?t=10"
  },
  {
    "id": "25",
    "name": "申し訳ないよぷねぷねぽむぽむ",
    "audioResourcePath": "/audio/mousiwakenaiyo.mp3",
    "youTubeVideoUrl": "https://www.youtube.com/shorts/VFROAk8WS4g?t=10"
  },
  {
    "id": "26",
    "name": "キタキタキタキタ-!2",
    "audioResourcePath": "/audio/kitakitakita2.mp3",
    "youTubeVideoUrl": "https://www.youtube.com/shorts/VFROAk8WS4g?t=10"
  },
  {
    "id": "28",
    "name": "おいしょ",
    "audioResourcePath": "/audio/oisyo.mp3",
    "youTubeVideoUrl": "https://www.youtube.com/shorts/VFROAk8WS4g?t=10"
  },
  {
    "id": "29",
    "name": "アハハ3",
    "audioResourcePath": "/audio/ahaha3.mp3",
    "youTubeVideoUrl": "https://www.youtube.com/shorts/VFROAk8WS4g?t=10"
  },
  {
    "id": "30",
    "name": "ダニエル↓くんオジですからこちら",
    "audioResourcePath": "/audio/danierukunozi.mp3",
    "youTubeVideoUrl": "https://www.youtube.com/shorts/VFROAk8WS4g?t=10"
  },
  {
    "id": "31",
    "name": "嬉しいありがとね",
    "audioResourcePath": "/audio/ureshiarigatone.mp3",
    "youTubeVideoUrl": "https://www.youtube.com/shorts/VFROAk8WS4g?t=10"
  },
  {
    "id": "32",
    "name": "申し訳ありません",
    "audioResourcePath": "/audio/moushiwakearimasen.mp3",
    "youTubeVideoUrl": "https://www.youtube.com/shorts/VFROAk8WS4g?t=10"
  },
  {
    "id": "33",
    "name": "スゥンスゥンスゥン",
    "audioResourcePath": "/audio/suunsuun.mp3",
    "youTubeVideoUrl": "https://www.youtube.com/shorts/VFROAk8WS4g?t=10"
  },
  {
    "id": "34",
    "name": "まずい",
    "audioResourcePath": "/audio/mazui.mp3",
    "youTubeVideoUrl": "https://www.youtube.com/shorts/VFROAk8WS4g?t=10"
  },
  {
    "id": "35",
    "name": "大変申し訳ありません",
    "audioResourcePath": "/audio/taihenmousiwakearimasen.mp3",
    "youTubeVideoUrl": "https://www.youtube.com/shorts/VFROAk8WS4g?t=10"
  },
  {
    "id": "36",
    "name": "あーやっちゃった",
    "audioResourcePath": "/audio/a-yachatta.mp3",
    "youTubeVideoUrl": "https://www.youtube.com/shorts/VFROAk8WS4g?t=10"
  },
  {
    "id": "37",
    "name": "あららら2",
    "audioResourcePath": "/audio/ararara2.mp3",
    "youTubeVideoUrl": "https://www.youtube.com/shorts/VFROAk8WS4g?t=10"
  },
  {
    "id": "38",
    "name": "逆ニコ・ロビン",
    "audioResourcePath": "/audio/igitakunai.mp3",
    "youTubeVideoUrl": "https://www.youtube.com/shorts/VFROAk8WS4g?t=10"
  },
  {
    "id": "39",
    "name": "とは思うんだけど、思うんだーけーどー",
    "audioResourcePath": "/audio/tohaomoundakedo.mp3",
    "youTubeVideoUrl": "https://www.youtube.com/shorts/VFROAk8WS4g?t=10"
  },
  {
    "id": "40",
    "name": "ギリ耐えた!",
    "audioResourcePath": "/audio/giritaeta.mp3",
    "youTubeVideoUrl": "https://www.youtube.com/shorts/VFROAk8WS4g?t=10"
  },
  {
    "id": "41",
    "name": "ね、それね、もうね",
    "audioResourcePath": "/audio/nesorenemoune.mp3",
    "youTubeVideoUrl": "https://www.youtube.com/shorts/VFROAk8WS4g?t=10"
  },
  {
    "id": "42",
    "name": "ほんとに？",
    "audioResourcePath": "/audio/hontoni.mp3",
    "youTubeVideoUrl": "https://www.youtube.com/shorts/VFROAk8WS4g?t=10"
  },
  {
    "id": "43",
    "name": "ちょっと待ってね",
    "audioResourcePath": "/audio/chottomattene.mp3",
    "youTubeVideoUrl": "https://www.youtube.com/shorts/VFROAk8WS4g?t=10"
  },
  {
    "id": "44",
    "name": "誘われてる？これ。ドキドキ",
    "audioResourcePath": "/audio/sasowareteru.mp3",
    "youTubeVideoUrl": "https://www.youtube.com/shorts/VFROAk8WS4g?t=10"
  },
  {
    "id": "45",
    "name": "キタァ!",
    "audioResourcePath": "/audio/kitaa.mp3",
    "youTubeVideoUrl": "https://www.youtube.com/shorts/VFROAk8WS4g?t=10"
  },
  {
    "id": "46",
    "name": "つれーよなあ",
    "audioResourcePath": "/audio/tureyona.mp3",
    "youTubeVideoUrl": "https://www.youtube.com/shorts/VFROAk8WS4g?t=10"
  },
  {
    "id": "47",
    "name": "ねえ！",
    "audioResourcePath": "/audio/nee.mp3",
    "youTubeVideoUrl": "https://www.youtube.com/shorts/VFROAk8WS4g?t=10"
  },
  {
    "id": "48",
    "name": "待ってどれだっけ",
    "audioResourcePath": "/audio/mattedoredakke.mp3",
    "youTubeVideoUrl": "https://www.youtube.com/shorts/VFROAk8WS4g?t=10"
  },
  {
    "id": "49",
    "name": "やだあ！",
    "audioResourcePath": "/audio/yadaa.mp3",
    "youTubeVideoUrl": "https://www.youtube.com/shorts/VFROAk8WS4g?t=10"
  },
  {
    "id": "50",
    "name": "みんなそれ求めてるから",
    "audioResourcePath": "/audio/minnnasoremotometeru.mp3",
    "youTubeVideoUrl": "https://www.youtube.com/shorts/VFROAk8WS4g?t=10"
  },
  {
    "id": "51",
    "name": "あれ!?",
    "audioResourcePath": "/audio/are.mp3",
    "youTubeVideoUrl": "https://www.youtube.com/shorts/VFROAk8WS4g?t=10"
  },
  {
    "id": "52",
    "name": "そういった噂があったわけ",
    "audioResourcePath": "/audio/uwasa.mp3",
    "youTubeVideoUrl": "https://www.youtube.com/shorts/VFROAk8WS4g?t=10"
  },
  {
    "id": "53",
    "name": "壺、やるってのかい!?",
    "audioResourcePath": "/audio/tsuboyaruttenokai.mp3",
    "youTubeVideoUrl": "https://www.youtube.com/shorts/VFROAk8WS4g?t=10"
  },
  {
    "id": "54",
    "name": "あーおっけおっけおっけ",
    "audioResourcePath": "/audio/a-okke.mp3",
    "youTubeVideoUrl": "https://www.youtube.com/shorts/VFROAk8WS4g?t=10"
  },
  {
    "id": "55",
    "name": "よっと、よっと、よっと",
    "audioResourcePath": "/audio/yotto*3.mp3",
    "youTubeVideoUrl": "https://www.youtube.com/shorts/VFROAk8WS4g?t=10"
  },
  {
    "id": "56",
    "name": "ありがたや〜",
    "audioResourcePath": "/audio/arigataya.mp3",
    "youTubeVideoUrl": "https://www.youtube.com/shorts/VFROAk8WS4g?t=10"
  }
]
